deapi/__init__.py
deapi/client.py
deapi/conf.py
deapi/data_types.py
deapi/index.rst
deapi/prop_dump.json
deapi/python_3_instruction.txt
deapi/release_notes.txt
deapi/utils.py
deapi/version.py
deapi/wrappers.py
deapi/buffer_protocols/__init__.py
deapi/buffer_protocols/pb_2_3_0.py
deapi/buffer_protocols/pb_3_11_4.py
deapi/buffer_protocols/pb_3_19_3.py
deapi/buffer_protocols/pb_3_23_3.py
deapi/buffer_protocols/pb_3_6_1.py
deapi/fake_data/__init__.py
deapi/fake_data/base_fake_data.py
deapi/fake_data/grains.py
deapi/service/de_service.py
deapi/simulated_server/__init__.py
deapi/simulated_server/fake_server.py
deapi/simulated_server/initialize_server.py
deapi/tests/__init__.py
deapi/tests/conftest.py
deapi/tests/test_client.py
deapi/tests/test_examples.py
deapi/tests/original_tests/01_fps.py
deapi/tests/original_tests/02_hwRoisize.py
deapi/tests/original_tests/03_hwBinning.py
deapi/tests/original_tests/04_swBinning.py
deapi/tests/original_tests/05_swhwBinning.py
deapi/tests/original_tests/06_patternPixel.py
deapi/tests/original_tests/07_reference.py
deapi/tests/original_tests/08_virtmask.py
deapi/tests/original_tests/09_scanRoi.py
deapi/tests/original_tests/10_imageStatistics.py
deapi/tests/original_tests/__init__.py
deapi/tests/original_tests/func.py
deapi/tests/original_tests/propertyName.py
deapi/tests/original_tests/test_legacy.py
deapi/tests/speed_tests/__init__.py
deapi/tests/speed_tests/test_internal_file_saving.py
deapi/tests/speed_tests/test_movie_buffer_transfer.py
deapi/tests/test_binning_rois/__init__.py
deapi/tests/test_binning_rois/test_rois.py
deapi/tests/test_fake_server/__init__.py
deapi/tests/test_fake_server/test_server.py
deapi/tests/test_file_saving/__init__.py
deapi/tests/test_file_saving/test_file_loading_libertem.py
deapi/tests/test_file_saving/test_file_loading_rsciio.py
deapi/tests/test_file_saving/test_h5ebsd.py
deapi/tests/test_file_saving/test_scan_pattern_saving.py
deapi/tests/test_insitu/__init__.py
deapi-5.2.2.dist-info/licenses/LICENSE
deapi-5.2.2.dist-info/METADATA
deapi-5.2.2.dist-info/WHEEL
deapi-5.2.2.dist-info/entry_points.txt
deapi-5.2.2.dist-info/top_level.txt
deapi-5.2.2.dist-info/RECORD
